_custom_build.py
telemed_sk/__init__.cpython-39-x86_64-linux-gnu.so
telemed_sk/algorithms/__init__.cpython-39-x86_64-linux-gnu.so
telemed_sk/algorithms/experiment.cpython-39-x86_64-linux-gnu.so
telemed_sk/algorithms/job.cpython-39-x86_64-linux-gnu.so
telemed_sk/algorithms/models.cpython-39-x86_64-linux-gnu.so
telemed_sk/algorithms/reconcile.cpython-39-x86_64-linux-gnu.so
telemed_sk/algorithms/utils.cpython-39-x86_64-linux-gnu.so
telemed_sk/analytics/__init__.cpython-39-x86_64-linux-gnu.so
telemed_sk/analytics/evaluationMetrics.cpython-39-x86_64-linux-gnu.so
telemed_sk/datahandler/__init__.cpython-39-x86_64-linux-gnu.so
telemed_sk/datahandler/datahandler.cpython-39-x86_64-linux-gnu.so
telemed_sk/datapreparation/__init__.cpython-39-x86_64-linux-gnu.so
telemed_sk/datapreparation/model_preproc.cpython-39-x86_64-linux-gnu.so
telemed_sk/datapreparation/preprocessing.cpython-39-x86_64-linux-gnu.so
telemed_sk/datapreparation/uc_preproc.cpython-39-x86_64-linux-gnu.so
telemed_sk/datapreparation/utils.cpython-39-x86_64-linux-gnu.so
telemed_sk/dataset/__init__.cpython-39-x86_64-linux-gnu.so
telemed_sk/utility/__init__.cpython-39-x86_64-linux-gnu.so
telemed_sk/utility/check_utils.cpython-39-x86_64-linux-gnu.so
telemed_sk/utility/configuration_utils.cpython-39-x86_64-linux-gnu.so
telemed_sk/utility/constants.cpython-39-x86_64-linux-gnu.so
telemed_sk/utility/exceptions.cpython-39-x86_64-linux-gnu.so
telemed_sk/utility/resources.cpython-39-x86_64-linux-gnu.so
telemed_sk/utility/tele_logger.cpython-39-x86_64-linux-gnu.so
telemed_sk-1.2.26.dist-info/METADATA
telemed_sk-1.2.26.dist-info/WHEEL
telemed_sk-1.2.26.dist-info/top_level.txt
telemed_sk-1.2.26.dist-info/RECORD
