Metadata-Version: 2.1
Name: telemed-sk
Version: 1.2.26
Summary: Lo scopo di questa libreria è fornire uno strumento completo per il rilascio di modelli predittivi basati su serie temporali nell'ambito della Telemedicina, al fine di supportare la gestione e la pianificazione delle attività sulla Piattaforma Nazionale di Telemedicina (PNT)
Classifier: Programming Language :: Python :: 3
Requires-Python: >=3.9
Requires-Dist: dtaidistance ==2.3.10
Requires-Dist: geopandas ==0.13.0
Requires-Dist: hierarchicalforecast ==0.3.0
Requires-Dist: holidays ==0.24
Requires-Dist: matplotlib ==3.7.1
Requires-Dist: mlflow ==1.27.0
Requires-Dist: pandas ==2.0.0
Requires-Dist: plotly ==5.14.1
Requires-Dist: prophet ==1.1.1
Requires-Dist: scikit-learn ==1.2.2
Requires-Dist: scipy ==1.11.1
Requires-Dist: seaborn ==0.12.2
Requires-Dist: statsmodels ==0.14.0
Requires-Dist: streamlit ==1.23.1
Requires-Dist: tabulate ==0.9.0
Requires-Dist: tomli ==2.0.1
Requires-Dist: typing-extensions ==4.7.1
Requires-Dist: xgboost ==1.7.6
Requires-Dist: fastparquet ==2023.7.0
Requires-Dist: telemedbasics >=1.7.6
